dude/__init__.py
dude/__main__.py
dude/_utils.py
dude/temp_toolbox.py
dude/_commands/__init__.py
dude/_commands/app.py
dude/_commands/cli_base.py
dude/_nu_local_env_defaults/__init__.py
dude/_nu_local_env_defaults/local.env
tests/__init__.py
tests/conftest.py
tests/test_app.py
tests/test_config.py
tests/test_main.py
tests/utils.py
tests/fixtures/formatting/kappa.py
tests/fixtures/requirements-only/app.py
tests/fixtures/requirements-only/requirements.in
tests/fixtures/requirements-only/requirements.txt
nubium_dude-5.1.0.post1.dist-info/METADATA
nubium_dude-5.1.0.post1.dist-info/WHEEL
nubium_dude-5.1.0.post1.dist-info/entry_points.txt
nubium_dude-5.1.0.post1.dist-info/top_level.txt
nubium_dude-5.1.0.post1.dist-info/RECORD
