Metadata-Version: 2.1
Name: nubium-dude
Version: 5.1.0.post1
Summary: Developer utilities to help manage nubium applications and other typical maintenance tasks
Home-page: https://gitlab.corp.redhat.com/mkt-ops-de/dude
Author: RedHat Marketing Operations Data Engineering
Author-email: mkt-ops-de@redhat.com,
License: MIT
Requires-Python: <3.10,>=3.8
Requires-Dist: black (<23.0,>=22.6.0)
Requires-Dist: click (<9.0.0,>=8.0.1)
Requires-Dist: jsonpath-ng
Requires-Dist: pydantic
Requires-Dist: python-dotenv (>=0.19.0)
Requires-Dist: pyyaml
Requires-Dist: virtualenv-api (<3.0.0,>=2.1.18)
Requires-Dist: virtualenv (<21.0.0,>=20.4.7)
Provides-Extra: docs
Requires-Dist: autodoc-pydantic ; extra == 'docs'
Requires-Dist: myst-parser ; extra == 'docs'
Requires-Dist: sphinx ; extra == 'docs'
Requires-Dist: sphinx-click ; extra == 'docs'
Requires-Dist: sphinx-rtd-theme ; extra == 'docs'
Provides-Extra: test
Requires-Dist: coverage[toml] ; extra == 'test'
Requires-Dist: pylint ; extra == 'test'
Requires-Dist: pytest (>=6.2.2) ; extra == 'test'
Requires-Dist: pytest-cov ; extra == 'test'
